<item>
<title>[COLOR blue]Shows here on day of event[/COLOR]</title>
<link></link>
<thumbnail></thumbnail> 
</item>

<item>
<title>[COLOR yellow]Twitter:@Cosmixrepo[/COLOR]</title>
<link>http://soccerinhd.com/hd1.html</link>
<thumbnail></thumbnail> 
</item>

<item>
<title>[COLOR yellow]David Haye vs Arnold Gjergjaj[/COLOR]</title>
<link>
<sublink>http://www.filmon.com/tv/dave</sublink>
<sublink>plugin://plugin.video.f4mTester/?streamtype=TSDOWNLOADER&amp;url=http://bit.ly/DaveUkCosmixLink</sublink>
<sublink>http://live9.net/live83.html</sublink>
<sublink>http://www.shadow-net.me/channels/Dave.html</sublink>
<sublink>http://hdfree.tv/watch/50/david-haye-vs.-arnold-gjergjaj.html</sublink>
</link>
<thumbnail></thumbnail> 
</item>
